RsCmwGsmSig/RsCmwGsmSig.py
RsCmwGsmSig/__init__.py
RsCmwGsmSig/enums.py
RsCmwGsmSig/repcap.py
RsCmwGsmSig/CustomFiles/__init__.py
RsCmwGsmSig/CustomFiles/events.py
RsCmwGsmSig/CustomFiles/reliability.py
RsCmwGsmSig/CustomFiles/utilities.py
RsCmwGsmSig/Implementations/Ber.py
RsCmwGsmSig/Implementations/Bler.py
RsCmwGsmSig/Implementations/Call.py
RsCmwGsmSig/Implementations/Clean.py
RsCmwGsmSig/Implementations/Configure.py
RsCmwGsmSig/Implementations/Cperformance.py
RsCmwGsmSig/Implementations/Cswitched.py
RsCmwGsmSig/Implementations/Handover.py
RsCmwGsmSig/Implementations/Intermediate.py
RsCmwGsmSig/Implementations/Prepare.py
RsCmwGsmSig/Implementations/Pswitched.py
RsCmwGsmSig/Implementations/Route.py
RsCmwGsmSig/Implementations/Sense.py
RsCmwGsmSig/Implementations/Source.py
RsCmwGsmSig/Implementations/Throughput.py
RsCmwGsmSig/Implementations/__init__.py
RsCmwGsmSig/Implementations/Ber_/Cswitched.py
RsCmwGsmSig/Implementations/Ber_/Pswitched.py
RsCmwGsmSig/Implementations/Ber_/__init__.py
RsCmwGsmSig/Implementations/Ber_/Cswitched_/State.py
RsCmwGsmSig/Implementations/Ber_/Cswitched_/__init__.py
RsCmwGsmSig/Implementations/Ber_/Cswitched_/State_/All.py
RsCmwGsmSig/Implementations/Ber_/Cswitched_/State_/__init__.py
RsCmwGsmSig/Implementations/Ber_/Pswitched_/Carrier.py
RsCmwGsmSig/Implementations/Ber_/Pswitched_/State.py
RsCmwGsmSig/Implementations/Ber_/Pswitched_/__init__.py
RsCmwGsmSig/Implementations/Ber_/Pswitched_/State_/All.py
RsCmwGsmSig/Implementations/Ber_/Pswitched_/State_/__init__.py
RsCmwGsmSig/Implementations/Bler_/Carrier.py
RsCmwGsmSig/Implementations/Bler_/Oall.py
RsCmwGsmSig/Implementations/Bler_/State.py
RsCmwGsmSig/Implementations/Bler_/__init__.py
RsCmwGsmSig/Implementations/Bler_/State_/All.py
RsCmwGsmSig/Implementations/Bler_/State_/__init__.py
RsCmwGsmSig/Implementations/Call_/Cswitched.py
RsCmwGsmSig/Implementations/Call_/Handover.py
RsCmwGsmSig/Implementations/Call_/Pswitched.py
RsCmwGsmSig/Implementations/Call_/__init__.py
RsCmwGsmSig-3.7.30.23.dist-info/METADATA
RsCmwGsmSig-3.7.30.23.dist-info/WHEEL
RsCmwGsmSig-3.7.30.23.dist-info/top_level.txt
RsCmwGsmSig-3.7.30.23.dist-info/RECORD
